sepm/__init__.py
sepm/config.py
sepm/exceptions.py
sepm/rest_api_session.py
sepm/endpoints/__init__.py
sepm/endpoints/administrators.py
sepm/endpoints/blacklist.py
sepm/endpoints/cloud.py
sepm/endpoints/commands.py
sepm/endpoints/computers.py
sepm/endpoints/content.py
sepm/endpoints/domains.py
sepm/endpoints/events.py
sepm/endpoints/group_update_provider.py
sepm/endpoints/groups.py
sepm/endpoints/identity.py
sepm/endpoints/notifications.py
sepm/endpoints/policies.py
sepm/endpoints/replication.py
sepm/endpoints/reporting.py
sepm/endpoints/requested_files.py
sepm/endpoints/statistics.py
sepm/endpoints/threat_defense_for_active_directory.py
sepm/endpoints/version.py
sepm_api-0.0.9.dist-info/LICENSE
sepm_api-0.0.9.dist-info/METADATA
sepm_api-0.0.9.dist-info/WHEEL
sepm_api-0.0.9.dist-info/top_level.txt
sepm_api-0.0.9.dist-info/RECORD
