Metadata-Version: 2.1
Name: sepm-api
Version: 0.0.9
Summary: Symantec Endpoint Protection Manager API
Home-page: https://github.com/aalmero/sepm-api
Author: Alex Almero
Author-email: aalmero@gmail.com
License: MIT
Classifier: Development Status :: 4 - Beta
Classifier: License :: OSI Approved :: MIT License
Classifier: Programming Language :: Python :: 3.7
Classifier: Programming Language :: Python :: 3.7
Classifier: Programming Language :: Python :: 3.8
Classifier: Programming Language :: Python :: 3.9
Classifier: Programming Language :: Python :: 3.10
Classifier: Programming Language :: Python :: 3.11
License-File: LICENSE
